scrapy_algolia_exporter/__init__.py
scrapy_algolia_exporter/exporters.py
scrapy_algolia_exporter/pipelines.py
scrapy_algolia_exporter-0.0.2.dist-info/DESCRIPTION.rst
scrapy_algolia_exporter-0.0.2.dist-info/METADATA
scrapy_algolia_exporter-0.0.2.dist-info/RECORD
scrapy_algolia_exporter-0.0.2.dist-info/WHEEL
scrapy_algolia_exporter-0.0.2.dist-info/metadata.json
scrapy_algolia_exporter-0.0.2.dist-info/top_level.txt
tests/__init__.py
tests/test_exporters.py
tests/test_pipelines.py
