Metadata-Version: 2.0
Name: scrapy-algolia-exporter
Version: 0.0.2
Summary: Scrapy item exporter for the Algolia API
Home-page: https://github.com/clemfromspace/scrapy-algolia-exporter
Author: UNKNOWN
Author-email: UNKNOWN
License: UNKNOWN
Platform: UNKNOWN
Requires-Dist: algoliasearch (==1.15.2)
Requires-Dist: Scrapy (>=1.0)
